nansi/__init__.py
nansi/constants.py
nansi/errors.py
nansi/os_resolve.py
nansi/proper.py
nansi/plugins/__init__.py
nansi/plugins/action/__init__.py
nansi/plugins/action/compose.py
nansi/plugins/action/defaults.py
nansi/plugins/action/os_resolve.py
nansi/plugins/action/args/__init__.py
nansi/plugins/action/args/all.py
nansi/plugins/action/args/arg.py
nansi/plugins/action/args/base.py
nansi/plugins/action/args/casts.py
nansi/plugins/action/args/errors.py
nansi/plugins/action/args/formatters.py
nansi/plugins/action/args/jsos.py
nansi/plugins/action/args/open.py
nansi/support/__init__.py
nansi/support/git.py
nansi/support/go.py
nansi/support/systemd.py
nansi/template/__init__.py
nansi/template/var_values.py
nansi/utils/__init__.py
nansi/utils/aliases.py
nansi/utils/casting.py
nansi/utils/cmds.py
nansi/utils/collections.py
nansi/utils/decorators.py
nansi/utils/doctesting.py
nansi/utils/functions.py
nansi/utils/logging.py
nansi/utils/paths.py
nansi/utils/strings.py
nansi/utils/text.py
nansi/utils/typings.py
nansi-0.1.1.dist-info/LICENSE
nansi-0.1.1.dist-info/METADATA
nansi-0.1.1.dist-info/WHEEL
nansi-0.1.1.dist-info/top_level.txt
nansi-0.1.1.dist-info/RECORD
