Metadata-Version: 2.1
Name: nansi
Version: 0.1.1
Summary: Nrser ANSIble
Home-page: https://nrser.com/nansi
Author: nrser
Author-email: neil@neilsouza.com
License: BSD License
Platform: POSIX
Classifier: Programming Language :: Python :: 3
Classifier: License :: OSI Approved :: BSD License
Classifier: Operating System :: POSIX
Requires-Python: >=3.8
Requires-Dist: ansible (<3,>=2.9.4)
Requires-Dist: typeguard (<3,>=2.9.1)
Requires-Dist: splatlog (>=0.1.0)
